quadre/__init__.py
quadre/__main__.py
quadre/api.py
quadre/cli.py
quadre/main.py
quadre/py.typed
quadre/theme.py
quadre/validator.py
quadre/components/__init__.py
quadre/components/cards.py
quadre/components/config.py
quadre/components/image.py
quadre/components/primitives.py
quadre/components/progress.py
quadre/components/status_badge.py
quadre/components/tables.py
quadre/flex/__init__.py
quadre/flex/adapter.py
quadre/flex/api.py
quadre/flex/defaults.py
quadre/flex/engine.py
quadre/flex/helpers.py
quadre/flex/runner.py
quadre/flex/widgets.py
quadre/plugins/__init__.py
quadre/plugins/builtin.py
quadre/plugins/registry.py
quadre/plugins/utils.py
quadre/theme/dark.json
quadre/theme/theme.json
quadre/utils/dataref.py
quadre-0.1.1.dist-info/METADATA
quadre-0.1.1.dist-info/WHEEL
quadre-0.1.1.dist-info/entry_points.txt
quadre-0.1.1.dist-info/licenses/LICENSE
quadre-0.1.1.dist-info/RECORD
