Metadata-Version: 2.4
Name: quadre
Version: 0.1.1
Summary: A Python CLI tool that generates beautiful dashboard images from JSON data using PIL/Pillow
Author-email: Quentin Amirault <amirault.quentin@gmail.com>
License: MIT License
License-File: LICENSE
Classifier: License :: OSI Approved :: MIT License
Classifier: Typing :: Typed
Requires-Python: >=3.12
Requires-Dist: pillow>=11.3.0
Requires-Dist: pydantic<3,>=2.7
